.travis.yml
CHANGES.rst
MANIFEST.in
README.rst
setup.py
payu/__init__.py
payu/payu.py
payu/test_core.py
payup.egg-info/PKG-INFO
payup.egg-info/SOURCES.txt
payup.egg-info/dependency_links.txt
payup.egg-info/not-zip-safe
payup.egg-info/requires.txt
payup.egg-info/top_level.txt