Metadata-Version: 1.1
Name: payup
Version: 0.0.2
Summary: A Python API for PayU Latam
Home-page: https://github.com/ajkaanbal/payu
Author: Ricardo M. Vilchis
Author-email: ajkaanba@gmail.com
License: MIT
Keywords: payu
Platform: UNKNOWN
Classifier: Programming Language :: Python :: 2.7
